{"name":"Login","id":"purchase-products-at-demoblaze;login","testSteps":[{"number":1,"description":"1: Login ({username\u003dSarai123, password\u003dSarai123})","duration":89,"startTime":"2023-05-05T16:00:36.982888900-05:00[America/Bogota]","result":"IGNORED","precondition":false,"level":0,"lineNumber":14,"children":[{"number":2,"description":"Given Sarai123 estoy en la pagina Demoblaze","duration":9,"startTime":"2023-05-05T16:00:37.029889800-05:00[America/Bogota]","result":"PENDING","precondition":false,"level":1},{"number":3,"description":"When ingresa sus credenciales de manera correcta Sarai123 Sarai123","duration":6,"startTime":"2023-05-05T16:00:37.044890100-05:00[America/Bogota]","result":"IGNORED","precondition":false,"level":1},{"number":4,"description":"Then se loguea de forma exitosa","duration":3,"startTime":"2023-05-05T16:00:37.052889300-05:00[America/Bogota]","result":"IGNORED","precondition":false,"level":1}]}],"userStory":{"id":"purchase-products-at-demoblaze","storyName":"Purchase products at Demoblaze","displayName":"Purchase products at Demoblaze","path":"shop.feature","type":"feature","qualifiedTag":{"name":"Purchase products at Demoblaze","type":"feature","displayName":"Purchase products at Demoblaze"}},"featureTag":{"name":"Purchase products at Demoblaze","type":"feature","displayName":"Purchase products at Demoblaze"},"title":"Login","description":"","tags":[{"name":"happyPath","type":"tag","displayName":"happyPath"},{"name":"Windows","type":"context","displayName":"Windows"},{"name":"Purchase products at Demoblaze","type":"feature","displayName":"Purchase products at Demoblaze"}],"allTags":[{"name":"happyPath","type":"tag","displayName":"happyPath"},{"name":"Windows","type":"context","displayName":"Windows"},{"name":"Purchase products at Demoblaze","type":"feature","displayName":"Purchase products at Demoblaze"}],"startTime":"2023-05-05T16:00:36.860889100-05:00[America/Bogota]","duration":216,"projectKey":"","annotatedResult":"PENDING","isManualTestingUpToDate":false,"context":"windows","dataTable":{"headers":["username","password"],"rows":[{"values":["Sarai123","Sarai123"],"lineNumber":14,"result":"PENDING"}],"predefinedRows":true,"scenarioOutline":"Given Sarai123 estoy en la pagina Demoblaze\n\rWhen ingresa sus credenciales de manera correcta \u003cusername\u003e \u003cpassword\u003e\n\rThen se loguea de forma exitosa\n\r","dataSetDescriptors":[{"startRow":0,"rowCount":0,"name":"","description":""}]},"manual":false,"testSource":"Cucumber","result":"PENDING","scenarioOutline":"Given Sarai123 estoy en la pagina Demoblaze\r\nWhen ingresa sus credenciales de manera correcta \u003cusername\u003e \u003cpassword\u003e\r\nThen se loguea de forma exitosa"}